MANIFEST.in
README.md
sed9ye3os.py
setup.py
sed9ye3os.egg-info/PKG-INFO
sed9ye3os.egg-info/SOURCES.txt
sed9ye3os.egg-info/dependency_links.txt
sed9ye3os.egg-info/top_level.txt